caspo_control/__init__.py
caspo_control/iface.py
caspo_control-1.0.dist-info/METADATA
caspo_control-1.0.dist-info/WHEEL
caspo_control-1.0.dist-info/top_level.txt
caspo_control-1.0.dist-info/RECORD
