Metadata-Version: 2.1
Name: caspo-control
Version: 1.0
Summary: Python wrapper for caspo control
Home-page: https://github.com/algorecell/caspo-control
Author: Loïc Paulevé
Author-email: loic.pauleve@labri.fr
License: UNKNOWN
Keywords: computational systems biology
Platform: UNKNOWN
Classifier: Intended Audience :: Science/Research
Classifier: Topic :: Scientific/Engineering :: Bio-Informatics
Requires-Dist: caspo
Requires-Dist: colomoto-jupyter
